[
  {
    "PM2.5": 41,
    "PM10": 104,
    "NO": "NA",
    "NO2": 40,
    "NOx": "NA",
    "NH3": 3,
    "SO2": 3,
    "CO": 66,
    "Ozone": 7,
    "date": "2025-04-25",
    "slot": "00:00-03:00"
  },
  {
    "PM2.5": 41,
    "PM10": 98,
    "NO": "NA",
    "NO2": 38,
    "NOx": "NA",
    "NH3": 3,
    "SO2": 2,
    "CO": 58,
    "Ozone": 5,
    "date": "2025-04-25",
    "slot": "03:00-06:00"
  },
  {
    "PM2.5": 43,
    "PM10": 106,
    "NO": "NA",
    "NO2": 40,
    "NOx": "NA",
    "NH3": 3,
    "SO2": 3,
    "CO": 53,
    "Ozone": 4,
    "date": "2025-04-25",
    "slot": "06:00-09:00"
  },
  {
    "PM2.5": 43,
    "PM10": 106,
    "NO": "NA",
    "NO2": 40,
    "NOx": "NA",
    "NH3": 3,
    "SO2": 3,
    "CO": 51,
    "Ozone": 4,
    "date": "2025-04-25",
    "slot": "09:00-12:00"
  },
  {
    "PM2.5": 43,
    "PM10": 108,
    "NO": "NA",
    "NO2": 40,
    "NOx": "NA",
    "NH3": 3,
    "SO2": 3,
    "CO": 53,
    "Ozone": 8,
    "date": "2025-04-25",
    "slot": "12:00-15:00"
  },
  {
    "PM2.5": 44,
    "PM10": 107,
    "NO": "NA",
    "NO2": 40,
    "NOx": "NA",
    "NH3": 3,
    "SO2": 3,
    "CO": 52,
    "Ozone": 11,
    "date": "2025-04-25",
    "slot": "15:00-18:00"
  },
  {
    "PM2.5": 43,
    "PM10": 109,
    "NO": "NA",
    "NO2": 40,
    "NOx": "NA",
    "NH3": 3,
    "SO2": 3,
    "CO": 57,
    "Ozone": 12,
    "date": "2025-04-25",
    "slot": "18:00-21:00"
  },
  {
    "PM2.5": 44,
    "PM10": 106,
    "NO": "NA",
    "NO2": 40,
    "NOx": "NA",
    "NH3": 3,
    "SO2": 3,
    "CO": 61,
    "Ozone": 10,
    "date": "2025-04-25",
    "slot": "21:00-24:00"
  },
  {
    "PM2.5": 46,
    "PM10": 105,
    "NO": "NA",
    "NO2": 40,
    "NOx": "NA",
    "NH3": 3,
    "SO2": 4,
    "CO": 66,
    "Ozone": 8,
    "date": "2025-04-26",
    "slot": "00:00-03:00"
  },
  {
    "PM2.5": 48,
    "PM10": 97,
    "NO": "NA",
    "NO2": 37,
    "NOx": "NA",
    "NH3": 3,
    "SO2": 4,
    "CO": 61,
    "Ozone": 7,
    "date": "2025-04-26",
    "slot": "03:00-06:00"
  },
  {
    "PM2.5": 48,
    "PM10": 102,
    "NO": "NA",
    "NO2": 39,
    "NOx": "NA",
    "NH3": 3,
    "SO2": 4,
    "CO": 57,
    "Ozone": 6,
    "date": "2025-04-26",
    "slot": "06:00-09:00"
  },
  {
    "PM2.5": 49,
    "PM10": 100,
    "NO": "NA",
    "NO2": 38,
    "NOx": "NA",
    "NH3": 3,
    "SO2": 4,
    "CO": 54,
    "Ozone": 5,
    "date": "2025-04-26",
    "slot": "09:00-12:00"
  },
  {
    "PM2.5": 49,
    "PM10": 98,
    "NO": "NA",
    "NO2": 38,
    "NOx": "NA",
    "NH3": 3,
    "SO2": 4,
    "CO": 55,
    "Ozone": 7,
    "date": "2025-04-26",
    "slot": "12:00-15:00"
  },
  {
    "PM2.5": 49,
    "PM10": 97,
    "NO": "NA",
    "NO2": 38,
    "NOx": "NA",
    "NH3": 3,
    "SO2": 4,
    "CO": 54,
    "Ozone": 10,
    "date": "2025-04-26",
    "slot": "15:00-18:00"
  },
  {
    "PM2.5": 48,
    "PM10": 95,
    "NO": "NA",
    "NO2": 37,
    "NOx": "NA",
    "NH3": 3,
    "SO2": 4,
    "CO": 59,
    "Ozone": 12,
    "date": "2025-04-26",
    "slot": "18:00-21:00"
  },
  {
    "PM2.5": 52,
    "PM10": 102,
    "NO": "NA",
    "NO2": 38,
    "NOx": "NA",
    "NH3": 3,
    "SO2": 3,
    "CO": 57,
    "Ozone": 12,
    "date": "2025-04-26",
    "slot": "21:00-24:00"
  },
  {
    "PM2.5": 50,
    "PM10": 99,
    "NO": "NA",
    "NO2": 38,
    "NOx": "NA",
    "NH3": 3,
    "SO2": 4,
    "CO": 62,
    "Ozone": 10,
    "date": "2025-04-27",
    "slot": "00:00-03:00"
  },
  {
    "PM2.5": 48,
    "PM10": 98,
    "NO": "NA",
    "NO2": 37,
    "NOx": "NA",
    "NH3": 3,
    "SO2": 4,
    "CO": 60,
    "Ozone": 8,
    "date": "2025-04-27",
    "slot": "03:00-06:00"
  },
  {
    "PM2.5": 48,
    "PM10": 96,
    "NO": "NA",
    "NO2": 37,
    "NOx": "NA",
    "NH3": 3,
    "SO2": 4,
    "CO": 58,
    "Ozone": 8,
    "date": "2025-04-27",
    "slot": "06:00-09:00"
  },
  {
    "PM2.5": 47,
    "PM10": 93,
    "NO": "NA",
    "NO2": 36,
    "NOx": "NA",
    "NH3": 3,
    "SO2": 4,
    "CO": 56,
    "Ozone": 6,
    "date": "2025-04-27",
    "slot": "09:00-12:00"
  },
  {
    "PM2.5": 44,
    "PM10": 90,
    "NO": "NA",
    "NO2": 36,
    "NOx": "NA",
    "NH3": 3,
    "SO2": 4,
    "CO": 58,
    "Ozone": 8,
    "date": "2025-04-27",
    "slot": "12:00-15:00"
  },
  {
    "PM2.5": 45,
    "PM10": 90,
    "NO": "NA",
    "NO2": 36,
    "NOx": "NA",
    "NH3": 3,
    "SO2": 4,
    "CO": 57,
    "Ozone": 10,
    "date": "2025-04-27",
    "slot": "15:00-18:00"
  },
  {
    "PM2.5": 43,
    "PM10": 87,
    "NO": "NA",
    "NO2": 36,
    "NOx": "NA",
    "NH3": 3,
    "SO2": 4,
    "CO": 61,
    "Ozone": 10,
    "date": "2025-04-27",
    "slot": "18:00-21:00"
  },
  {
    "PM2.5": 48,
    "PM10": 96,
    "NO": "NA",
    "NO2": 38,
    "NOx": "NA",
    "NH3": 3,
    "SO2": 4,
    "CO": 55,
    "Ozone": 10,
    "date": "2025-04-27",
    "slot": "21:00-24:00"
  },
  {
    "PM2.5": 41,
    "PM10": 103,
    "NO": "NA",
    "NO2": 40,
    "NOx": "NA",
    "NH3": 3,
    "SO2": 4,
    "CO": 53,
    "Ozone": 9,
    "date": "2025-04-28",
    "slot": "00:00-03:00"
  },
  {
    "PM2.5": 41,
    "PM10": 84,
    "NO": "NA",
    "NO2": 41,
    "NOx": "NA",
    "NH3": 3,
    "SO2": 4,
    "CO": 66,
    "Ozone": 8,
    "date": "2025-04-28",
    "slot": "03:00-06:00"
  },
  {
    "PM2.5": 49,
    "PM10": 83,
    "NO": "NA",
    "NO2": 40,
    "NOx": "NA",
    "NH3": 3,
    "SO2": 5,
    "CO": 66,
    "Ozone": 8,
    "date": "2025-04-28",
    "slot": "06:00-09:00"
  },
  {
    "PM2.5": 38,
    "PM10": 97,
    "NO": "NA",
    "NO2": 32,
    "NOx": "NA",
    "NH3": 3,
    "SO2": 5,
    "CO": 54,
    "Ozone": 7,
    "date": "2025-04-28",
    "slot": "09:00-12:00"
  },
  {
    "PM2.5": 45,
    "PM10": 96,
    "NO": "NA",
    "NO2": 31,
    "NOx": "NA",
    "NH3": 3,
    "SO2": 5,
    "CO": 54,
    "Ozone": 7,
    "date": "2025-04-28",
    "slot": "12:00-15:00"
  },
  {
    "PM2.5": 37,
    "PM10": 77,
    "NO": "NA",
    "NO2": 31,
    "NOx": "NA",
    "NH3": 3,
    "SO2": 4,
    "CO": 55,
    "Ozone": 10,
    "date": "2025-04-28",
    "slot": "15:00-18:00"
  },
  {
    "PM2.5": 37,
    "PM10": 77,
    "NO": "NA",
    "NO2": 32,
    "NOx": "NA",
    "NH3": 3,
    "SO2": 5,
    "CO": 69,
    "Ozone": 9,
    "date": "2025-04-28",
    "slot": "18:00-21:00"
  },
  {
    "PM2.5": 43,
    "PM10": 91,
    "NO": "NA",
    "NO2": 43,
    "NOx": "NA",
    "NH3": 3,
    "SO2": 4,
    "CO": 52,
    "Ozone": 10,
    "date": "2025-04-28",
    "slot": "21:00-24:00"
  },
  {
    "PM2.5": 52,
    "PM10": 106,
    "NO": "NA",
    "NO2": 36,
    "NOx": "NA",
    "NH3": 3,
    "SO2": 3,
    "CO": 60,
    "Ozone": 10,
    "date": "2025-04-29",
    "slot": "00:00-03:00"
  },
  {
    "PM2.5": 43,
    "PM10": 106,
    "NO": "NA",
    "NO2": 44,
    "NOx": "NA",
    "NH3": 3,
    "SO2": 4,
    "CO": 49,
    "Ozone": 10,
    "date": "2025-04-29",
    "slot": "03:00-06:00"
  },
  {
    "PM2.5": 43,
    "PM10": 106,
    "NO": "NA",
    "NO2": 36,
    "NOx": "NA",
    "NH3": 3,
    "SO2": 4,
    "CO": 60,
    "Ozone": 12,
    "date": "2025-04-29",
    "slot": "06:00-09:00"
  },
  {
    "PM2.5": 43,
    "PM10": 106,
    "NO": "NA",
    "NO2": 36,
    "NOx": "NA",
    "NH3": 3,
    "SO2": 3,
    "CO": 60,
    "Ozone": 10,
    "date": "2025-04-29",
    "slot": "09:00-12:00"
  },
  {
    "PM2.5": 52,
    "PM10": 87,
    "NO": "NA",
    "NO2": 36,
    "NOx": "NA",
    "NH3": 3,
    "SO2": 4,
    "CO": 49,
    "Ozone": 12,
    "date": "2025-04-29",
    "slot": "12:00-15:00"
  },
  {
    "PM2.5": 52,
    "PM10": 87,
    "NO": "NA",
    "NO2": 36,
    "NOx": "NA",
    "NH3": 3,
    "SO2": 4,
    "CO": 49,
    "Ozone": 10,
    "date": "2025-04-29",
    "slot": "15:00-18:00"
  },
  {
    "PM2.5": 52,
    "PM10": 87,
    "NO": "NA",
    "NO2": 44,
    "NOx": "NA",
    "NH3": 3,
    "SO2": 4,
    "CO": 60,
    "Ozone": 12,
    "date": "2025-04-29",
    "slot": "18:00-21:00"
  },
  {
    "PM2.5": 52,
    "PM10": 106,
    "NO": "NA",
    "NO2": 36,
    "NOx": "NA",
    "NH3": 3,
    "SO2": 3,
    "CO": 60,
    "Ozone": 10,
    "date": "2025-04-29",
    "slot": "21:00-24:00"
  },
  {
    "PM2.5": 52,
    "PM10": 88,
    "NO": "NA",
    "NO2": 43,
    "NOx": "NA",
    "NH3": 3,
    "SO2": 4,
    "CO": 50,
    "Ozone": 11,
    "date": "2025-04-30",
    "slot": "00:00-03:00"
  },
  {
    "PM2.5": 52,
    "PM10": 107,
    "NO": "NA",
    "NO2": 43,
    "NOx": "NA",
    "NH3": 3,
    "SO2": 3,
    "CO": 50,
    "Ozone": 9,
    "date": "2025-04-30",
    "slot": "03:00-06:00"
  },
  {
    "PM2.5": 52,
    "PM10": 107,
    "NO": "NA",
    "NO2": 35,
    "NOx": "NA",
    "NH3": 3,
    "SO2": 4,
    "CO": 61,
    "Ozone": 11,
    "date": "2025-04-30",
    "slot": "06:00-09:00"
  },
  {
    "PM2.5": 43,
    "PM10": 107,
    "NO": "NA",
    "NO2": 43,
    "NOx": "NA",
    "NH3": 3,
    "SO2": 3,
    "CO": 50,
    "Ozone": 9,
    "date": "2025-04-30",
    "slot": "09:00-12:00"
  },
  {
    "PM2.5": 52,
    "PM10": 88,
    "NO": "NA",
    "NO2": 35,
    "NOx": "NA",
    "NH3": 3,
    "SO2": 4,
    "CO": 50,
    "Ozone": 9,
    "date": "2025-04-30",
    "slot": "12:00-15:00"
  },
  {
    "PM2.5": 52,
    "PM10": 88,
    "NO": "NA",
    "NO2": 35,
    "NOx": "NA",
    "NH3": 3,
    "SO2": 4,
    "CO": 61,
    "Ozone": 11,
    "date": "2025-04-30",
    "slot": "15:00-18:00"
  },
  {
    "PM2.5": 52,
    "PM10": 88,
    "NO": "NA",
    "NO2": 43,
    "NOx": "NA",
    "NH3": 3,
    "SO2": 4,
    "CO": 50,
    "Ozone": 9,
    "date": "2025-04-30",
    "slot": "18:00-21:00"
  },
  {
    "PM2.5": 43,
    "PM10": 88,
    "NO": "NA",
    "NO2": 35,
    "NOx": "NA",
    "NH3": 3,
    "SO2": 3,
    "CO": 61,
    "Ozone": 9,
    "date": "2025-04-30",
    "slot": "21:00-24:00"
  }
]