[
  {
    "PM2.5": 100,
    "PM10": 113,
    "NO": "NA",
    "NO2": 4,
    "NOx": "NA",
    "NH3": 1,
    "SO2": "NA",
    "CO": 5,
    "Ozone": 28,
    "date": "2025-04-25",
    "slot": "00:00-03:00"
  },
  {
    "PM2.5": 98,
    "PM10": 106,
    "NO": "NA",
    "NO2": 4,
    "NOx": "NA",
    "NH3": 1,
    "SO2": "NA",
    "CO": 4,
    "Ozone": 28,
    "date": "2025-04-25",
    "slot": "03:00-06:00"
  },
  {
    "PM2.5": 109,
    "PM10": 116,
    "NO": "NA",
    "NO2": 4,
    "NOx": "NA",
    "NH3": 1,
    "SO2": "NA",
    "CO": 5,
    "Ozone": 28,
    "date": "2025-04-25",
    "slot": "06:00-09:00"
  },
  {
    "PM2.5": 113,
    "PM10": 115,
    "NO": "NA",
    "NO2": 4,
    "NOx": "NA",
    "NH3": 1,
    "SO2": "NA",
    "CO": 5,
    "Ozone": 28,
    "date": "2025-04-25",
    "slot": "09:00-12:00"
  },
  {
    "PM2.5": 113,
    "PM10": 114,
    "NO": "NA",
    "NO2": 4,
    "NOx": "NA",
    "NH3": 1,
    "SO2": "NA",
    "CO": 4,
    "Ozone": 28,
    "date": "2025-04-25",
    "slot": "12:00-15:00"
  },
  {
    "PM2.5": 106,
    "PM10": 114,
    "NO": "NA",
    "NO2": 4,
    "NOx": "NA",
    "NH3": 1,
    "SO2": "NA",
    "CO": 4,
    "Ozone": 28,
    "date": "2025-04-25",
    "slot": "15:00-18:00"
  },
  {
    "PM2.5": 105,
    "PM10": 115,
    "NO": "NA",
    "NO2": 4,
    "NOx": "NA",
    "NH3": 1,
    "SO2": "NA",
    "CO": 4,
    "Ozone": 28,
    "date": "2025-04-25",
    "slot": "18:00-21:00"
  },
  {
    "PM2.5": 97,
    "PM10": 115,
    "NO": "NA",
    "NO2": 4,
    "NOx": "NA",
    "NH3": 1,
    "SO2": "NA",
    "CO": 4,
    "Ozone": 28,
    "date": "2025-04-25",
    "slot": "21:00-24:00"
  },
  {
    "PM2.5": 93,
    "PM10": 116,
    "NO": "NA",
    "NO2": 4,
    "NOx": "NA",
    "NH3": 1,
    "SO2": "NA",
    "CO": 5,
    "Ozone": 28,
    "date": "2025-04-26",
    "slot": "00:00-03:00"
  },
  {
    "PM2.5": 93,
    "PM10": 112,
    "NO": "NA",
    "NO2": 4,
    "NOx": "NA",
    "NH3": 1,
    "SO2": "NA",
    "CO": 4,
    "Ozone": 28,
    "date": "2025-04-26",
    "slot": "03:00-06:00"
  },
  {
    "PM2.5": 99,
    "PM10": 118,
    "NO": "NA",
    "NO2": 4,
    "NOx": "NA",
    "NH3": 1,
    "SO2": "NA",
    "CO": 5,
    "Ozone": 28,
    "date": "2025-04-26",
    "slot": "06:00-09:00"
  },
  {
    "PM2.5": 102,
    "PM10": 116,
    "NO": "NA",
    "NO2": 4,
    "NOx": "NA",
    "NH3": 1,
    "SO2": "NA",
    "CO": 5,
    "Ozone": 28,
    "date": "2025-04-26",
    "slot": "09:00-12:00"
  },
  {
    "PM2.5": 101,
    "PM10": 115,
    "NO": "NA",
    "NO2": 4,
    "NOx": "NA",
    "NH3": 1,
    "SO2": "NA",
    "CO": 4,
    "Ozone": 28,
    "date": "2025-04-26",
    "slot": "12:00-15:00"
  },
  {
    "PM2.5": 99,
    "PM10": 114,
    "NO": "NA",
    "NO2": 4,
    "NOx": "NA",
    "NH3": 1,
    "SO2": "NA",
    "CO": 4,
    "Ozone": 28,
    "date": "2025-04-26",
    "slot": "15:00-18:00"
  },
  {
    "PM2.5": 104,
    "PM10": 118,
    "NO": "NA",
    "NO2": 4,
    "NOx": "NA",
    "NH3": 1,
    "SO2": "NA",
    "CO": 3,
    "Ozone": 28,
    "date": "2025-04-26",
    "slot": "18:00-21:00"
  },
  {
    "PM2.5": 97,
    "PM10": 114,
    "NO": "NA",
    "NO2": 4,
    "NOx": "NA",
    "NH3": 1,
    "SO2": "NA",
    "CO": 3,
    "Ozone": 28,
    "date": "2025-04-26",
    "slot": "21:00-24:00"
  },
  {
    "PM2.5": 94,
    "PM10": 112,
    "NO": "NA",
    "NO2": 4,
    "NOx": "NA",
    "NH3": 1,
    "SO2": "NA",
    "CO": 4,
    "Ozone": 28,
    "date": "2025-04-27",
    "slot": "00:00-03:00"
  },
  {
    "PM2.5": 94,
    "PM10": 112,
    "NO": "NA",
    "NO2": 4,
    "NOx": "NA",
    "NH3": 1,
    "SO2": "NA",
    "CO": 4,
    "Ozone": 28,
    "date": "2025-04-27",
    "slot": "03:00-06:00"
  },
  {
    "PM2.5": 92,
    "PM10": 110,
    "NO": "NA",
    "NO2": 4,
    "NOx": "NA",
    "NH3": 1,
    "SO2": "NA",
    "CO": 4,
    "Ozone": 28,
    "date": "2025-04-27",
    "slot": "06:00-09:00"
  },
  {
    "PM2.5": 91,
    "PM10": 109,
    "NO": "NA",
    "NO2": 4,
    "NOx": "NA",
    "NH3": 1,
    "SO2": "NA",
    "CO": 4,
    "Ozone": 28,
    "date": "2025-04-27",
    "slot": "09:00-12:00"
  },
  {
    "PM2.5": 90,
    "PM10": 108,
    "NO": "NA",
    "NO2": 4,
    "NOx": "NA",
    "NH3": 1,
    "SO2": "NA",
    "CO": 4,
    "Ozone": 28,
    "date": "2025-04-27",
    "slot": "12:00-15:00"
  },
  {
    "PM2.5": 89,
    "PM10": 107,
    "NO": "NA",
    "NO2": 4,
    "NOx": "NA",
    "NH3": 1,
    "SO2": "NA",
    "CO": 4,
    "Ozone": 28,
    "date": "2025-04-27",
    "slot": "15:00-18:00"
  },
  {
    "PM2.5": 91,
    "PM10": 110,
    "NO": "NA",
    "NO2": 4,
    "NOx": "NA",
    "NH3": 1,
    "SO2": "NA",
    "CO": 3,
    "Ozone": 28,
    "date": "2025-04-27",
    "slot": "18:00-21:00"
  },
  {
    "PM2.5": 90,
    "PM10": 109,
    "NO": "NA",
    "NO2": 4,
    "NOx": "NA",
    "NH3": 1,
    "SO2": "NA",
    "CO": 3,
    "Ozone": 28,
    "date": "2025-04-27",
    "slot": "21:00-24:00"
  },
  {
    "PM2.5": 81,
    "PM10": 98,
    "NO": "NA",
    "NO2": 4,
    "NOx": "NA",
    "NH3": 1,
    "SO2": "NA",
    "CO": 3,
    "Ozone": 31,
    "date": "2025-04-28",
    "slot": "00:00-03:00"
  },
  {
    "PM2.5": 82,
    "PM10": 99,
    "NO": "NA",
    "NO2": 4,
    "NOx": "NA",
    "NH3": 1,
    "SO2": "NA",
    "CO": 3,
    "Ozone": 31,
    "date": "2025-04-28",
    "slot": "03:00-06:00"
  },
  {
    "PM2.5": 82,
    "PM10": 120,
    "NO": "NA",
    "NO2": 4,
    "NOx": "NA",
    "NH3": 1,
    "SO2": "NA",
    "CO": 4,
    "Ozone": 31,
    "date": "2025-04-28",
    "slot": "06:00-09:00"
  },
  {
    "PM2.5": 80,
    "PM10": 97,
    "NO": "NA",
    "NO2": 3,
    "NOx": "NA",
    "NH3": 1,
    "SO2": "NA",
    "CO": 4,
    "Ozone": 31,
    "date": "2025-04-28",
    "slot": "09:00-12:00"
  },
  {
    "PM2.5": 98,
    "PM10": 97,
    "NO": "NA",
    "NO2": 4,
    "NOx": "NA",
    "NH3": 1,
    "SO2": "NA",
    "CO": 4,
    "Ozone": 25,
    "date": "2025-04-28",
    "slot": "12:00-15:00"
  },
  {
    "PM2.5": 80,
    "PM10": 118,
    "NO": "NA",
    "NO2": 4,
    "NOx": "NA",
    "NH3": 1,
    "SO2": "NA",
    "CO": 3,
    "Ozone": 31,
    "date": "2025-04-28",
    "slot": "15:00-18:00"
  },
  {
    "PM2.5": 85,
    "PM10": 101,
    "NO": "NA",
    "NO2": 4,
    "NOx": "NA",
    "NH3": 1,
    "SO2": "NA",
    "CO": 3,
    "Ozone": 25,
    "date": "2025-04-28",
    "slot": "18:00-21:00"
  },
  {
    "PM2.5": 85,
    "PM10": 101,
    "NO": "NA",
    "NO2": 4,
    "NOx": "NA",
    "NH3": 1,
    "SO2": "NA",
    "CO": 4,
    "Ozone": 25,
    "date": "2025-04-28",
    "slot": "21:00-24:00"
  },
  {
    "PM2.5": 82,
    "PM10": 119,
    "NO": "NA",
    "NO2": 4,
    "NOx": "NA",
    "NH3": 1,
    "SO2": "NA",
    "CO": 3,
    "Ozone": 24,
    "date": "2025-04-29",
    "slot": "00:00-03:00"
  },
  {
    "PM2.5": 100,
    "PM10": 97,
    "NO": "NA",
    "NO2": 4,
    "NOx": "NA",
    "NH3": 1,
    "SO2": "NA",
    "CO": 4,
    "Ozone": 30,
    "date": "2025-04-29",
    "slot": "03:00-06:00"
  },
  {
    "PM2.5": 82,
    "PM10": 119,
    "NO": "NA",
    "NO2": 4,
    "NOx": "NA",
    "NH3": 1,
    "SO2": "NA",
    "CO": 3,
    "Ozone": 24,
    "date": "2025-04-29",
    "slot": "06:00-09:00"
  },
  {
    "PM2.5": 82,
    "PM10": 97,
    "NO": "NA",
    "NO2": 4,
    "NOx": "NA",
    "NH3": 1,
    "SO2": "NA",
    "CO": 4,
    "Ozone": 30,
    "date": "2025-04-29",
    "slot": "09:00-12:00"
  },
  {
    "PM2.5": 100,
    "PM10": 119,
    "NO": "NA",
    "NO2": 4,
    "NOx": "NA",
    "NH3": 1,
    "SO2": "NA",
    "CO": 4,
    "Ozone": 30,
    "date": "2025-04-29",
    "slot": "12:00-15:00"
  },
  {
    "PM2.5": 82,
    "PM10": 97,
    "NO": "NA",
    "NO2": 4,
    "NOx": "NA",
    "NH3": 1,
    "SO2": "NA",
    "CO": 3,
    "Ozone": 30,
    "date": "2025-04-29",
    "slot": "15:00-18:00"
  },
  {
    "PM2.5": 100,
    "PM10": 119,
    "NO": "NA",
    "NO2": 4,
    "NOx": "NA",
    "NH3": 1,
    "SO2": "NA",
    "CO": 4,
    "Ozone": 30,
    "date": "2025-04-29",
    "slot": "18:00-21:00"
  },
  {
    "PM2.5": 100,
    "PM10": 97,
    "NO": "NA",
    "NO2": 4,
    "NOx": "NA",
    "NH3": 1,
    "SO2": "NA",
    "CO": 3,
    "Ozone": 24,
    "date": "2025-04-29",
    "slot": "21:00-24:00"
  },
  {
    "PM2.5": 82,
    "PM10": 113,
    "NO": "NA",
    "NO2": 4,
    "NOx": "NA",
    "NH3": 1,
    "SO2": "NA",
    "CO": 3,
    "Ozone": 28,
    "date": "2025-04-30",
    "slot": "00:00-03:00"
  },
  {
    "PM2.5": 82,
    "PM10": 113,
    "NO": "NA",
    "NO2": 4,
    "NOx": "NA",
    "NH3": 1,
    "SO2": "NA",
    "CO": 4,
    "Ozone": 28,
    "date": "2025-04-30",
    "slot": "03:00-06:00"
  },
  {
    "PM2.5": 101,
    "PM10": 92,
    "NO": "NA",
    "NO2": 4,
    "NOx": "NA",
    "NH3": 1,
    "SO2": "NA",
    "CO": 4,
    "Ozone": 28,
    "date": "2025-04-30",
    "slot": "06:00-09:00"
  },
  {
    "PM2.5": 82,
    "PM10": 113,
    "NO": "NA",
    "NO2": 4,
    "NOx": "NA",
    "NH3": 1,
    "SO2": "NA",
    "CO": 3,
    "Ozone": 28,
    "date": "2025-04-30",
    "slot": "09:00-12:00"
  },
  {
    "PM2.5": 101,
    "PM10": 113,
    "NO": "NA",
    "NO2": 4,
    "NOx": "NA",
    "NH3": 1,
    "SO2": "NA",
    "CO": 4,
    "Ozone": 23,
    "date": "2025-04-30",
    "slot": "12:00-15:00"
  },
  {
    "PM2.5": 82,
    "PM10": 92,
    "NO": "NA",
    "NO2": 4,
    "NOx": "NA",
    "NH3": 1,
    "SO2": "NA",
    "CO": 4,
    "Ozone": 23,
    "date": "2025-04-30",
    "slot": "15:00-18:00"
  },
  {
    "PM2.5": 101,
    "PM10": 92,
    "NO": "NA",
    "NO2": 4,
    "NOx": "NA",
    "NH3": 1,
    "SO2": "NA",
    "CO": 4,
    "Ozone": 28,
    "date": "2025-04-30",
    "slot": "18:00-21:00"
  },
  {
    "PM2.5": 82,
    "PM10": 113,
    "NO": "NA",
    "NO2": 4,
    "NOx": "NA",
    "NH3": 1,
    "SO2": "NA",
    "CO": 4,
    "Ozone": 23,
    "date": "2025-04-30",
    "slot": "21:00-24:00"
  }
]