[
  {
    "PM2.5": 29,
    "PM10": 92,
    "NO": "NA",
    "NO2": 51,
    "NOx": "NA",
    "NH3": 11,
    "SO2": 7,
    "CO": 41,
    "Ozone": 11,
    "date": "2025-06-09",
    "slot": "00:00-03:00"
  },
  {
    "PM2.5": 30,
    "PM10": 92,
    "NO": "NA",
    "NO2": 52,
    "NOx": "NA",
    "NH3": 11,
    "SO2": 6,
    "CO": 46,
    "Ozone": 5,
    "date": "2025-06-09",
    "slot": "03:00-06:00"
  },
  {
    "PM2.5": 30,
    "PM10": 92,
    "NO": "NA",
    "NO2": 53,
    "NOx": "NA",
    "NH3": 11,
    "SO2": 6,
    "CO": 44,
    "Ozone": 4,
    "date": "2025-06-09",
    "slot": "06:00-09:00"
  },
  {
    "PM2.5": 29,
    "PM10": 90,
    "NO": "NA",
    "NO2": 53,
    "NOx": "NA",
    "NH3": 11,
    "SO2": 7,
    "CO": 36,
    "Ozone": 6,
    "date": "2025-06-09",
    "slot": "09:00-12:00"
  },
  {
    "PM2.5": 28,
    "PM10": 89,
    "NO": "NA",
    "NO2": 53,
    "NOx": "NA",
    "NH3": 10,
    "SO2": 7,
    "CO": 29,
    "Ozone": 12,
    "date": "2025-06-09",
    "slot": "12:00-15:00"
  },
  {
    "PM2.5": 28,
    "PM10": 87,
    "NO": "NA",
    "NO2": 52,
    "NOx": "NA",
    "NH3": 10,
    "SO2": 7,
    "CO": 25,
    "Ozone": 17,
    "date": "2025-06-09",
    "slot": "15:00-18:00"
  },
  {
    "PM2.5": 27,
    "PM10": 86,
    "NO": "NA",
    "NO2": 50,
    "NOx": "NA",
    "NH3": 10,
    "SO2": 6,
    "CO": 23,
    "Ozone": 21,
    "date": "2025-06-09",
    "slot": "18:00-21:00"
  },
  {
    "PM2.5": 25,
    "PM10": 83,
    "NO": "NA",
    "NO2": 47,
    "NOx": "NA",
    "NH3": 10,
    "SO2": 7,
    "CO": 27,
    "Ozone": 18,
    "date": "2025-06-09",
    "slot": "21:00-24:00"
  },
  {
    "PM2.5": 23,
    "PM10": 81,
    "NO": "NA",
    "NO2": 44,
    "NOx": "NA",
    "NH3": 10,
    "SO2": 7,
    "CO": 33,
    "Ozone": 14,
    "date": "2025-06-10",
    "slot": "00:00-03:00"
  },
  {
    "PM2.5": 23,
    "PM10": 80,
    "NO": "NA",
    "NO2": 43,
    "NOx": "NA",
    "NH3": 10,
    "SO2": 6,
    "CO": 36,
    "Ozone": 10,
    "date": "2025-06-10",
    "slot": "03:00-06:00"
  },
  {
    "PM2.5": 21,
    "PM10": 77,
    "NO": "NA",
    "NO2": 40,
    "NOx": "NA",
    "NH3": 9,
    "SO2": 7,
    "CO": 33,
    "Ozone": 10,
    "date": "2025-06-10",
    "slot": "06:00-09:00"
  },
  {
    "PM2.5": 19,
    "PM10": 75,
    "NO": "NA",
    "NO2": 38,
    "NOx": "NA",
    "NH3": 9,
    "SO2": 7,
    "CO": 26,
    "Ozone": 11,
    "date": "2025-06-10",
    "slot": "09:00-12:00"
  },
  {
    "PM2.5": 18,
    "PM10": 74,
    "NO": "NA",
    "NO2": 38,
    "NOx": "NA",
    "NH3": 8,
    "SO2": 6,
    "CO": 21,
    "Ozone": 15,
    "date": "2025-06-10",
    "slot": "12:00-15:00"
  },
  {
    "PM2.5": 21,
    "PM10": 74,
    "NO": "NA",
    "NO2": 46,
    "NOx": "NA",
    "NH3": 9,
    "SO2": 7,
    "CO": 22,
    "Ozone": 18,
    "date": "2025-06-10",
    "slot": "15:00-18:00"
  },
  {
    "PM2.5": 20,
    "PM10": 75,
    "NO": "NA",
    "NO2": 46,
    "NOx": "NA",
    "NH3": 9,
    "SO2": 6,
    "CO": 20,
    "Ozone": 22,
    "date": "2025-06-10",
    "slot": "18:00-21:00"
  },
  {
    "PM2.5": 21,
    "PM10": 75,
    "NO": "NA",
    "NO2": 45,
    "NOx": "NA",
    "NH3": 10,
    "SO2": 6,
    "CO": 23,
    "Ozone": 19,
    "date": "2025-06-10",
    "slot": "21:00-24:00"
  },
  {
    "PM2.5": 19,
    "PM10": 75,
    "NO": "NA",
    "NO2": 44,
    "NOx": "NA",
    "NH3": 10,
    "SO2": 6,
    "CO": 29,
    "Ozone": 16,
    "date": "2025-06-11",
    "slot": "00:00-03:00"
  },
  {
    "PM2.5": 19,
    "PM10": 74,
    "NO": "NA",
    "NO2": 43,
    "NOx": "NA",
    "NH3": 9,
    "SO2": 6,
    "CO": 32,
    "Ozone": 13,
    "date": "2025-06-11",
    "slot": "03:00-06:00"
  },
  {
    "PM2.5": 19,
    "PM10": 76,
    "NO": "NA",
    "NO2": 42,
    "NOx": "NA",
    "NH3": 9,
    "SO2": 6,
    "CO": 32,
    "Ozone": 12,
    "date": "2025-06-11",
    "slot": "06:00-09:00"
  },
  {
    "PM2.5": 18,
    "PM10": 76,
    "NO": "NA",
    "NO2": 42,
    "NOx": "NA",
    "NH3": 9,
    "SO2": 6,
    "CO": 28,
    "Ozone": 12,
    "date": "2025-06-11",
    "slot": "09:00-12:00"
  },
  {
    "PM2.5": 18,
    "PM10": 77,
    "NO": "NA",
    "NO2": 41,
    "NOx": "NA",
    "NH3": 9,
    "SO2": 6,
    "CO": 23,
    "Ozone": 15,
    "date": "2025-06-11",
    "slot": "12:00-15:00"
  },
  {
    "PM2.5": 24,
    "PM10": 80,
    "NO": "NA",
    "NO2": 54,
    "NOx": "NA",
    "NH3": 10,
    "SO2": 6,
    "CO": 25,
    "Ozone": 19,
    "date": "2025-06-11",
    "slot": "15:00-18:00"
  },
  {
    "PM2.5": 24,
    "PM10": 81,
    "NO": "NA",
    "NO2": 53,
    "NOx": "NA",
    "NH3": 10,
    "SO2": 6,
    "CO": 21,
    "Ozone": 20,
    "date": "2025-06-11",
    "slot": "18:00-21:00"
  },
  {
    "PM2.5": 22,
    "PM10": 82,
    "NO": "NA",
    "NO2": 49,
    "NOx": "NA",
    "NH3": 10,
    "SO2": 6,
    "CO": 18,
    "Ozone": 19,
    "date": "2025-06-11",
    "slot": "21:00-24:00"
  },
  {
    "PM2.5": 23,
    "PM10": 89,
    "NO": "NA",
    "NO2": 40,
    "NOx": "NA",
    "NH3": 9,
    "SO2": 7,
    "CO": 18,
    "Ozone": 19,
    "date": "2025-06-12",
    "slot": "00:00-03:00"
  },
  {
    "PM2.5": 21,
    "PM10": 87,
    "NO": "NA",
    "NO2": 38,
    "NOx": "NA",
    "NH3": 11,
    "SO2": 6,
    "CO": 15,
    "Ozone": 19,
    "date": "2025-06-12",
    "slot": "03:00-06:00"
  },
  {
    "PM2.5": 16,
    "PM10": 70,
    "NO": "NA",
    "NO2": 42,
    "NOx": "NA",
    "NH3": 8,
    "SO2": 6,
    "CO": 14,
    "Ozone": 19,
    "date": "2025-06-12",
    "slot": "06:00-09:00"
  },
  {
    "PM2.5": 15,
    "PM10": 85,
    "NO": "NA",
    "NO2": 30,
    "NOx": "NA",
    "NH3": 10,
    "SO2": 7,
    "CO": 14,
    "Ozone": 15,
    "date": "2025-06-12",
    "slot": "09:00-12:00"
  },
  {
    "PM2.5": 14,
    "PM10": 85,
    "NO": "NA",
    "NO2": 36,
    "NOx": "NA",
    "NH3": 9,
    "SO2": 7,
    "CO": 15,
    "Ozone": 15,
    "date": "2025-06-12",
    "slot": "12:00-15:00"
  },
  {
    "PM2.5": 20,
    "PM10": 88,
    "NO": "NA",
    "NO2": 42,
    "NOx": "NA",
    "NH3": 9,
    "SO2": 7,
    "CO": 20,
    "Ozone": 21,
    "date": "2025-06-12",
    "slot": "15:00-18:00"
  },
  {
    "PM2.5": 25,
    "PM10": 72,
    "NO": "NA",
    "NO2": 42,
    "NOx": "NA",
    "NH3": 9,
    "SO2": 7,
    "CO": 25,
    "Ozone": 17,
    "date": "2025-06-12",
    "slot": "18:00-21:00"
  },
  {
    "PM2.5": 25,
    "PM10": 88,
    "NO": "NA",
    "NO2": 52,
    "NOx": "NA",
    "NH3": 9,
    "SO2": 6,
    "CO": 25,
    "Ozone": 17,
    "date": "2025-06-12",
    "slot": "21:00-24:00"
  },
  {
    "PM2.5": 20,
    "PM10": 74,
    "NO": "NA",
    "NO2": 44,
    "NOx": "NA",
    "NH3": 11,
    "SO2": 7,
    "CO": 24,
    "Ozone": 16,
    "date": "2025-06-13",
    "slot": "00:00-03:00"
  },
  {
    "PM2.5": 20,
    "PM10": 90,
    "NO": "NA",
    "NO2": 54,
    "NOx": "NA",
    "NH3": 9,
    "SO2": 7,
    "CO": 24,
    "Ozone": 20,
    "date": "2025-06-13",
    "slot": "03:00-06:00"
  },
  {
    "PM2.5": 25,
    "PM10": 74,
    "NO": "NA",
    "NO2": 44,
    "NOx": "NA",
    "NH3": 9,
    "SO2": 5,
    "CO": 24,
    "Ozone": 16,
    "date": "2025-06-13",
    "slot": "06:00-09:00"
  },
  {
    "PM2.5": 25,
    "PM10": 74,
    "NO": "NA",
    "NO2": 44,
    "NOx": "NA",
    "NH3": 11,
    "SO2": 7,
    "CO": 20,
    "Ozone": 20,
    "date": "2025-06-13",
    "slot": "09:00-12:00"
  },
  {
    "PM2.5": 25,
    "PM10": 90,
    "NO": "NA",
    "NO2": 54,
    "NOx": "NA",
    "NH3": 11,
    "SO2": 7,
    "CO": 24,
    "Ozone": 20,
    "date": "2025-06-13",
    "slot": "12:00-15:00"
  },
  {
    "PM2.5": 25,
    "PM10": 90,
    "NO": "NA",
    "NO2": 54,
    "NOx": "NA",
    "NH3": 11,
    "SO2": 5,
    "CO": 24,
    "Ozone": 20,
    "date": "2025-06-13",
    "slot": "15:00-18:00"
  },
  {
    "PM2.5": 25,
    "PM10": 74,
    "NO": "NA",
    "NO2": 44,
    "NOx": "NA",
    "NH3": 11,
    "SO2": 7,
    "CO": 24,
    "Ozone": 20,
    "date": "2025-06-13",
    "slot": "18:00-21:00"
  },
  {
    "PM2.5": 25,
    "PM10": 74,
    "NO": "NA",
    "NO2": 44,
    "NOx": "NA",
    "NH3": 9,
    "SO2": 7,
    "CO": 20,
    "Ozone": 16,
    "date": "2025-06-13",
    "slot": "21:00-24:00"
  },
  {
    "PM2.5": 22,
    "PM10": 73,
    "NO": "NA",
    "NO2": 44,
    "NOx": "NA",
    "NH3": 10,
    "SO2": 6,
    "CO": 23,
    "Ozone": 19,
    "date": "2025-06-14",
    "slot": "00:00-03:00"
  },
  {
    "PM2.5": 22,
    "PM10": 89,
    "NO": "NA",
    "NO2": 53,
    "NOx": "NA",
    "NH3": 10,
    "SO2": 7,
    "CO": 19,
    "Ozone": 16,
    "date": "2025-06-14",
    "slot": "03:00-06:00"
  },
  {
    "PM2.5": 26,
    "PM10": 73,
    "NO": "NA",
    "NO2": 53,
    "NOx": "NA",
    "NH3": 10,
    "SO2": 7,
    "CO": 23,
    "Ozone": 19,
    "date": "2025-06-14",
    "slot": "06:00-09:00"
  },
  {
    "PM2.5": 26,
    "PM10": 89,
    "NO": "NA",
    "NO2": 44,
    "NOx": "NA",
    "NH3": 10,
    "SO2": 7,
    "CO": 19,
    "Ozone": 19,
    "date": "2025-06-14",
    "slot": "09:00-12:00"
  },
  {
    "PM2.5": 22,
    "PM10": 73,
    "NO": "NA",
    "NO2": 53,
    "NOx": "NA",
    "NH3": 8,
    "SO2": 7,
    "CO": 23,
    "Ozone": 16,
    "date": "2025-06-14",
    "slot": "12:00-15:00"
  },
  {
    "PM2.5": 22,
    "PM10": 73,
    "NO": "NA",
    "NO2": 44,
    "NOx": "NA",
    "NH3": 8,
    "SO2": 7,
    "CO": 19,
    "Ozone": 16,
    "date": "2025-06-14",
    "slot": "15:00-18:00"
  },
  {
    "PM2.5": 26,
    "PM10": 89,
    "NO": "NA",
    "NO2": 53,
    "NOx": "NA",
    "NH3": 8,
    "SO2": 7,
    "CO": 23,
    "Ozone": 16,
    "date": "2025-06-14",
    "slot": "18:00-21:00"
  },
  {
    "PM2.5": 22,
    "PM10": 73,
    "NO": "NA",
    "NO2": 53,
    "NOx": "NA",
    "NH3": 10,
    "SO2": 7,
    "CO": 23,
    "Ozone": 19,
    "date": "2025-06-14",
    "slot": "21:00-24:00"
  }
]